btcid/__init__.py
btcid/api.py
btcid-0.1.0.data/data/LICENSE.txt
btcid-0.1.0.dist-info/DESCRIPTION.rst
btcid-0.1.0.dist-info/LICENSE.txt
btcid-0.1.0.dist-info/METADATA
btcid-0.1.0.dist-info/RECORD
btcid-0.1.0.dist-info/WHEEL
btcid-0.1.0.dist-info/metadata.json
btcid-0.1.0.dist-info/top_level.txt
