Metadata-Version: 2.0
Name: btcid
Version: 0.1.0
Summary: Python wrapper for bitcoin.co.id API
Home-page: https://github.com/chickenzord/btcid-py
Author: Akhyar Amarullah
Author-email: akhyrul@gmail.com
License: MIT
Download-URL: https://github.com/chickenzord/btcid-py/archive/v0.1.0.tar.gz
Keywords: cryptocurrency,bitcoin,indonesia
Platform: UNKNOWN
Classifier: Development Status :: 4 - Beta
Classifier: License :: OSI Approved :: MIT License
Classifier: Intended Audience :: Developers
Classifier: Operating System :: POSIX :: Linux
Classifier: Programming Language :: Python
Classifier: Programming Language :: Python :: 2.7
Classifier: Programming Language :: Python :: 3.3
Classifier: Programming Language :: Python :: 3.4
Classifier: Programming Language :: Python :: 3.5
Classifier: Programming Language :: Python :: 3.6
Classifier: Topic :: Software Development :: Libraries
Requires-Dist: requests
Requires-Dist: future
